Workbook

Sheet Monthly Data
A1: Year | B1: Month | C1: Budget | D1: Actual | E1: Variance Amount | F1: Variance %
A2: 2021 | B2: Jan | C2: 21587408 | D2: 24913213 | E2: 3325805 | F2: 0.1541
B3: Feb | C3: 18142623 | D3: 20632263 | E3: 2489640 | F3: 0.1372
B4: Mar | C4: 19747700 | D4: 24295909 | E4: 4548209 | F4: 0.2303
B5: Apr | C5: 19710246 | D5: 24364104 | E5: 4653858 | F5: 0.2361
B6: May | C6: 24597175 | D6: 27250381 | E6: 2653206 | F6: 0.1079
B7: Jun | C7: 22265011 | D7: 22396228 | E7: 131217 | F7: 0.0059
B8: Jul | C8: 21471995 | D8: 24685975 | E8: 3213980 | F8: 0.1497
B9: Aug | C9: 23607929 | D9: 25003789 | E9: 1395860 | F9: 0.0591
B10: Sep | C10: 22494061 | D10: 25829986 | E10: 3335925 | F10: 0.1483
B11: Oct | C11: 19594167 | D11: 22180032 | E11: 2585865 | F11: 0.132
B12: Nov | C12: 21683155 | D12: 22968470 | E12: 1285315 | F12: 0.0593
B13: Dec | C13: 21779550 | D13: 22990736 | E13: 1211186 | F13: 0.0556
A14: 2022 | B14: Jan | C14: 23546292 | D14: 26727517 | E14: 3181225 | F14: 0.1351
B15: Feb | C15: 19296156 | D15: 21186138 | E15: 1889982 | F15: 0.0979
B16: Mar | C16: 20905031 | D16: 24891811 | E16: 3986780 | F16: 0.1907
B17: Apr | C17: 20561645 | D17: 24055215 | E17: 3493570 | F17: 0.1699
B18: May | C18: 22751826 | D18: 26605506 | E18: 3853680 | F18: 0.1694
B19: Jun | C19: 22687896 | D19: 24875581 | E19: 2187685 | F19: 0.0964
B20: Jul | C20: 23703274 | D20: 26115690 | E20: 2412416 | F20: 0.1018
B21: Aug | C21: 22779028 | D21: 26201877 | E21: 3422849 | F21: 0.1503
B22: Sep | C22: 21101758 | D22: 23615228 | E22: 2513470 | F22: 0.1191
B23: Oct | C23: 24781493 | D23: 26499256 | E23: 1717763 | F23: 0.0693
B24: Nov | C24: 21084652 | D24: 23619293 | E24: 2534641 | F24: 0.1202
B25: Dec | C25: 23235485 | D25: 28476038 | E25: 5240553 | F25: 0.2255
A26: 2023 | B26: Jan | C26: 22135628 | D26: 22670612 | E26: 534984 | F26: 0.0242
B27: Feb | C27: 19393433 | D27: 22714535 | E27: 3321102 | F27: 0.1712
B28: Mar | C28: 23064909 | D28: 24144517 | E28: 1079608 | F28: 0.0468
B29: Apr | C29: 26078247 | D29: 29230433 | E29: 3152186 | F29: 0.1209
B30: May | C30: 23256181 | D30: 24725549 | E30: 1469368 | F30: 0.0632
B31: Jun | C31: 22281988 | D31: 23994290 | E31: 1712302 | F31: 0.0768
B32: Jul | C32: 24964894 | D32: 28433347 | E32: 3468453 | F32: 0.1389
B33: Aug | C33: 22068703 | D33: 25209565 | E33: 3140862 | F33: 0.1423
B34: Sep | C34: 23636341 | D34: 25829660 | E34: 2193319 | F34: 0.0928
B35: Oct | C35: 21324454 | D35: 24008371 | E35: 2683917 | F35: 0.1259
B36: Nov | C36: 21286372 | D36: 22933724 | E36: 1647352 | F36: 0.0774
B37: Dec | C37: 22964822 | D37: 26106531 | E37: 3141709 | F37: 0.1368

Sheet Department Analysis
A1: Department | B1: Budget | C1: Actual | D1: Variance Amount | E1: Variance % | G1: Row Labels | H1: Sum of Variance Amount
A2: Marketing | B2: 131939479 | C2: 151816098 | D2: 19876619 | E2: =SUM(department_performance[[#This Row],[Variance Amount ]]/department_performance[[#This Row],[Budget]]) -> 0.15064952 | G2: Finance | H2: 11137380
A3: HR | B3: 137371163 | C3: 155439763 | D3: 18068600 | E3: =SUM(department_performance[[#This Row],[Variance Amount ]]/department_performance[[#This Row],[Budget]]) -> 0.13153124 | G3: HR | H3: 18068600
A4: Sales | B4: 134804760 | C4: 151459340 | D4: 16654580 | E4: =SUM(department_performance[[#This Row],[Variance Amount ]]/department_performance[[#This Row],[Budget]]) -> 0.12354593 | G4: IT | H4: 13892025
A5: Operations | B5: 132622213 | C5: 147803987 | D5: 15181774 | E5: =SUM(department_performance[[#This Row],[Variance Amount ]]/department_performance[[#This Row],[Budget]]) -> 0.11447384 | G5: Marketing | H5: 19876619
A6: IT | B6: 125771001 | C6: 139663026 | D6: 13892025 | E6: =SUM(department_performance[[#This Row],[Variance Amount ]]/department_performance[[#This Row],[Budget]]) -> 0.11045491 | G6: Operations | H6: 15181774
A7: Finance | B7: 132947149 | C7: 144084529 | D7: 11137380 | E7: =SUM(department_performance[[#This Row],[Variance Amount ]]/department_performance[[#This Row],[Budget]]) -> 0.083772989 | G7: Sales | H7: 16654580
G8: Grand Total | H8: 94810978

Sheet Category Analysis
A1: Category | B1: Budget | C1: Actual | D1: Variance Amount | E1: Variance % | G1: Row Labels | H1: Sum of Budget | I1: Sum of Actual
A2: Salaries | B2: 127131160 | C2: 147744247 | D2: 20613087 | E2: =SUM(category_performance[[#This Row],[Variance Amount ]]/category_performance[[#This Row],[Budget]]) -> 0.16214032 | G2: Infrastructure | H2: 127813870 | I2: 140825422
A3: Utilities | B3: 137891618 | C3: 155260320 | D3: 17368702 | E3: =SUM(category_performance[[#This Row],[Variance Amount ]]/category_performance[[#This Row],[Budget]]) -> 0.12595908 | G3: Marketing | H3: 130224132 | I3: 146525696
A4: Marketing | B4: 130224132 | C4: 146525696 | D4: 16301564 | E4: =SUM(category_performance[[#This Row],[Variance Amount ]]/category_performance[[#This Row],[Budget]]) -> 0.12518082 | G4: Salaries | H4: 127131160 | I4: 147744247
A5: Travel | B5: 140071130 | C5: 154999674 | D5: 14928544 | E5: =SUM(category_performance[[#This Row],[Variance Amount ]]/category_performance[[#This Row],[Budget]]) -> 0.10657831 | G5: Training | H5: 132399473 | I5: 145010926
A6: Infrastructure | B6: 127813870 | C6: 140825422 | D6: 13011552 | E6: =SUM(category_performance[[#This Row],[Variance Amount ]]/category_performance[[#This Row],[Budget]]) -> 0.10180078 | G6: Travel | H6: 140071130 | I6: 154999674
A7: Training | B7: 132399473 | C7: 145010926 | D7: 12611453 | E7: =SUM(category_performance[[#This Row],[Variance Amount ]]/category_performance[[#This Row],[Budget]]) -> 0.095253045 | G7: Utilities | H7: 137891618 | I7: 155260320
G8: Grand Total | H8: 795531383 | I8: 890366285

Sheet Region Analysis
A1: Region | B1: Budget | C1: Actual | D1: Variance Amount | E1: Variance % | G1: Row Labels | H1: Sum of Variance Amount
A2: East | B2: 159685797 | C2: 181076974 | D2: 21391177 | E2: =SUM(region_performance[[#This Row],[Variance Amount ]]/region_performance[[#This Row],[Budget]]) -> 0.13395792 | G2: Central | H2: 19432887
A3: Central | B3: 162759606 | C3: 182192493 | D3: 19432887 | E3: =SUM(region_performance[[#This Row],[Variance Amount ]]/region_performance[[#This Row],[Budget]]) -> 0.11939625 | G3: East | H3: 21391177
A4: South | B4: 157991439 | C4: 176760699 | D4: 18769260 | E4: =SUM(region_performance[[#This Row],[Variance Amount ]]/region_performance[[#This Row],[Budget]]) -> 0.11879922 | G4: North | H4: 16532154
A5: West | B5: 157004504 | C5: 175505843 | D5: 18501339 | E5: =SUM(region_performance[[#This Row],[Variance Amount ]]/region_performance[[#This Row],[Budget]]) -> 0.11783954 | G5: South | H5: 18769260
A6: North | B6: 157929548 | C6: 174461702 | D6: 16532154 | E6: =SUM(region_performance[[#This Row],[Variance Amount ]]/region_performance[[#This Row],[Budget]]) -> 0.10468056 | G6: West | H6: 18501339
G7: Grand Total | H7: 94626817

Sheet Forecast 2023
A1: Month | B1: Budget | C1: Actual
A2: Jan | B2: 22135628 | C2: 22670612
A3: Feb | B3: 19393433 | C3: 22714535
A4: Mar | B4: 23064909 | C4: 24144517
A5: Apr | B5: 26078247 | C5: 29230433
A6: May | B6: 23256181 | C6: 24725549
A7: Jun | B7: 22281988 | C7: 23994290
A8: Jul | B8: 24964894 | C8: 28433347
A9: Aug | B9: 22068703 | C9: 25209565
A10: Sep | B10: 23636341 | C10: 25829660
A11: Oct | B11: 21324454 | C11: 24008371
A12: Nov | B12: 21286372 | C12: 22933724
A13: Dec | B13: 22964822 | C13: 26106531
A15: Month | B15: Budget | C15: Actual | D15: Actual Used | E15: Forecast | F15: Variance to Budget | H15: YTD Run Rate Factor | I15: =SUM(D16:D24)/SUM(B16:B24) -> 1.0970232
A16: Jan | B16: 22135628 | C16: 22670612 | D16: 22670612 | E16: =D16 -> 22670612 | F16: =E16-B16 -> 534984
A17: Feb | B17: 19393433 | C17: 22714535 | D17: 22714535 | E17: =D17 -> 22714535 | F17: =E17-B17 -> 3321102
A18: Mar | B18: 23064909 | C18: 24144517 | D18: 24144517 | E18: =D18 -> 24144517 | F18: =E18-B18 -> 1079608
A19: Apr | B19: 26078247 | C19: 29230433 | D19: 29230433 | E19: =D19 -> 29230433 | F19: =E19-B19 -> 3152186
A20: May | B20: 23256181 | C20: 24725549 | D20: 24725549 | E20: =D20 -> 24725549 | F20: =E20-B20 -> 1469368
A21: Jun | B21: 22281988 | C21: 23994290 | D21: 23994290 | E21: =D21 -> 23994290 | F21: =E21-B21 -> 1712302
A22: Jul | B22: 24964894 | C22: 28433347 | D22: 28433347 | E22: =D22 -> 28433347 | F22: =E22-B22 -> 3468453
A23: Aug | B23: 22068703 | C23: 25209565 | D23: 25209565 | E23: =D23 -> 25209565 | F23: =E23-B23 -> 3140862
A24: Sep | B24: 23636341 | C24: 25829660 | D24: 25829660 | E24: =D24 -> 25829660 | F24: =E24-B24 -> 2193319
A25: Oct | B25: 21324454 | C25: 24008371 | D25: / | E25: =B25*$I$15 -> 23393420 | F25: =E25-B25 -> 2068966 | H25: ** Yellow indicates Q4 Forecast
A26: Nov | B26: 21286372 | C26: 22933724 | D26: / | E26: =B26*$I$15 -> 23351643 | F26: =E26-B26 -> 2065271.2
A27: Dec | B27: 22964822 | C27: 26106531 | D27: / | E27: =B27*$I$15 -> 25192942 | F27: =E27-B27 -> 2228119.7
A28: Total | B28: =SUM(B16:B27) -> 272455972 | C28: =SUM(Table6[Actual]) -> 300001134 | E28: =SUM(Table6[Forecast]) -> 2.9889051e+08 | F28: =SUBTOTAL(109,Table6[Variance to Budget]) -> 26434541
A30: 2023 Forecast Table
A31: 2023 Budget | B31: =SUM(forecast_2023_input[[Budget ]]) -> 272455972
A32: 2023 Forecast | B32: =SUM(Table6[Forecast]) -> 2.9889051e+08
A33: 2023 Actual | B33: =SUM(forecast_2023_input[Actual]) -> 300001134
A34: Forecast Error ($) | B34: =Table6[[#Totals],[Forecast]]-Table6[[#Totals],[Actual]] -> -1110621
A35: Forecast Error (%) | B35: =(Table6[[#Totals],[Forecast]]-Table6[[#Totals],[Actual]])/Table6[[#Totals],[Actual]] -> -0.0037020561
A36: Forecast vs Budget | B36: =(B32-B31)/B31 -> 0.097023166

Sheet Scenario Analysis
A1: 2023 Scenario Analysis
A3: Scenario | B3: Q4 Adjustment | C3: Q4 Forecast | D3: Jan-Sept Actual | E3: Full-Year Forecast | F3: Variance to Budget | G3: Variance %
A4: Low Spend | B4: -0.05 | C4: =SUM('Forecast 2023'!E25:E27)*(1+'Scenario Analysis'!B4) -> 68341105 | D4: =SUM('Forecast 2023'!D16:D24) -> 226952508 | E4: =D4+C4 -> 2.9529361e+08 | F4: =E4-Table6[[#Totals],[Budget ]] -> 22837641 | G4: =F4/Table6[[#Totals],[Budget ]] -> 0.083821399
A5: Base Case | B5: 0 | C5: =SUM('Forecast 2023'!E25:E27)*('Scenario Analysis'!B5+1) -> 71938005 | D5: =SUM('Forecast 2023'!D16:D24) -> 226952508 | E5: =D5+C5 -> 2.9889051e+08 | F5: =E5-Table6[[#Totals],[Budget ]] -> 26434541 | G5: =F5/Table6[[#Totals],[Budget ]] -> 0.097023166
A6: High Spend | B6: 0.05 | C6: =SUM('Forecast 2023'!E25:E27)*('Scenario Analysis'!B6+1) -> 75534905 | D6: =SUM('Forecast 2023'!D16:D24) -> 226952508 | E6: =D6+C6 -> 3.0248741e+08 | F6: =E6-Table6[[#Totals],[Budget ]] -> 30031441 | G6: =F6/Table6[[#Totals],[Budget ]] -> 0.11022493
A8: Scenario | B8: Full Year Spend
A9: Budget | B9: =Table6[[#Totals],[Budget ]] -> 272455972
A10: Low Spend | B10: =E4 -> 2.9529361e+08
A11: Base Case | B11: =E5 -> 2.9889051e+08
A12: High Spend | B12: =E6 -> 3.0248741e+08

Sheet Dashboard
B1: FP&A Actual vs Budget Dashboard
B3: 2021-2023 Financial Performance, Forecasting and Scenario Analysis
B5: Total Budget | E5: Total Actual | H5: Total Variance | K5: Variance | N5: 2023 Forecast
B6: =GETPIVOTDATA("Sum of Budget",'Category Analysis'!$G$1) -> 795531383 | E6: =GETPIVOTDATA("Sum of Actual",'Category Analysis'!$G$1) -> 890366285 | H6: =SUM('Category Analysis'!D2:D7) -> 94834902 | K6: =H6/B6 -> 0.1192095 | N6: ='Scenario Analysis'!E5 -> 2.9889051e+08
C8: 2023 Budget | H8: 2023 Actual | L8: Forecast Variance %
C9: =SUM(forecast_2023_input[[Budget ]]) -> 272455972 | H9: ='Forecast 2023'!C28 -> 300001134 | L9: =-('Forecast 2023'!B32-'Forecast 2023'!B33)/'Forecast 2023'!B33 -> 0.0037020561
R15: Key Insights:
Q17: Budget Perfomance:
Q18: Actual spending exceed the $795.5M budget by approximately $94.8M (unfavorable Variance of 11.9%)
Q23: Primary Cost Driver:
Q24: Marketing generated the largest departmental unfavorable variance at approximately $19.9M
Q29: Forecast and Scenario Analysis:
Q30: September YTD performance projected full-year spending of $298.9M against a $272.5M budget. The forecast finished within 0.4% of actual year-end spending, while scenario analysis showed spending remaining above budget even with Q4 spend 5% below forecast
